arcane/googleads/__init__.py
arcane/googleads/client.py
arcane/googleads/exceptions.py
arcane/googleads/helpers.py
arcane_googleads-3.16.1.dist-info/METADATA
arcane_googleads-3.16.1.dist-info/WHEEL
arcane_googleads-3.16.1.dist-info/RECORD
