Metadata-Version: 2.3
Name: arcane-googleads
Version: 3.16.1
Summary: Un package pour interagir avec l'API Google Ads
Author: Arcane
Author-email: product@wearcane.com
Requires-Python: >=3.9,<3.14
Classifier: Programming Language :: Python :: 3
Classifier: Programming Language :: Python :: 3.9
Classifier: Programming Language :: Python :: 3.10
Classifier: Programming Language :: Python :: 3.11
Classifier: Programming Language :: Python :: 3.12
Classifier: Programming Language :: Python :: 3.13
Requires-Dist: arcane-core (>=1.7.0,<2.0.0)
Requires-Dist: arcane-credentials (>=0.1.0,<0.2.0)
Requires-Dist: arcane-datastore (>=1.0,<2.0)
Requires-Dist: arcane-requests (>=0,<1)
Requires-Dist: backoff (>=1.10.0)
Requires-Dist: google-ads (==26.0.1)
Requires-Dist: pyyaml (>=5.1,<7.0)
